bmp_lib/__init__.py
bmp_lib/bmp_func.py
bmp_lib-0.2.dist-info/LICENSE
bmp_lib-0.2.dist-info/METADATA
bmp_lib-0.2.dist-info/WHEEL
bmp_lib-0.2.dist-info/top_level.txt
bmp_lib-0.2.dist-info/RECORD
