Metadata-Version: 2.2
Name: bmp_lib
Version: 0.2
Summary: This package implements all the logic of Brief My Press.AI
Author-email: Taoufiq OUEDRAOGO <taoufiq2827.ouedraogo@gmail.com>
License: Copyright (c) 2018 The Python Packaging Authority
Project-URL: Homepage, https://github.com/Taoufiq-Ouedraogo/Brief-My-Press-AI-Library
Classifier: Programming Language :: Python :: 3
Classifier: Operating System :: OS Independent
Requires-Python: <3.11,>=3.10
License-File: LICENSE
Requires-Dist: setuptools
Requires-Dist: wheel
Requires-Dist: twine
Requires-Dist: ipywidgets
Requires-Dist: transformers
Requires-Dist: openai
Requires-Dist: python-dotenv
Requires-Dist: spacy
Requires-Dist: gTTS
Requires-Dist: pandas
Requires-Dist: ipykernel
Requires-Dist: requests
Requires-Dist: openpyxl
Requires-Dist: mlx-lm
